<?xml version="1.0"?>
<?xml-stylesheet type="text/xsl" href="../../../xsl/imgfile.xsl"?>
<!DOCTYPE imgfile.content SYSTEM "../../../dtd/text.ent">
<imgfile.content module="Device_marking" file="armexpg2.xml">
<img src="armexpg2.gif">
<img.area shape="rect" coords="172,15,319,36" href="../device_marking/sys/4_info_reqs.xml#Device_marking_arm.message_source_select" />
<img.area shape="rect" coords="10,10,102,31" href="../device_marking/sys/4_info_reqs.xml#Device_marking_arm.message_type" />
<img.area shape="rect" coords="320,160,469,181" href="../device_marking/sys/4_info_reqs.xml#Device_marking_arm.marked_message_select" />
<img.area shape="rect" coords="320,332,482,359" href="../styled_text/sys/4_info_reqs.xml#Styled_text_arm.Styled_text" />

<img.area shape="rect" coords="29,65,231,94" href="../device_marking/sys/4_info_reqs.xml#Device_marking_arm.Configuration_controlled_message" />
<img.area shape="rect" coords="320,250,596,277" href="../elemental_geometric_shape/sys/4_info_reqs.xml#Elemental_geometric_shape_arm.Axis_placement" />
<img.area shape="rect" coords="320,212,602,239" href="../pdm_material_aspects/sys/4_info_reqs.xml#Pdm_material_aspects_arm.Material_identification" />

<img.area shape="rect" coords="411,71,591,113" href="../characteristic/sys/4_info_reqs.xml#Characteristic_arm.Text_representation_item" />
<img.area shape="rect" coords="320,293,458,314" href="../device_marking/sys/4_info_reqs.xml#Device_marking_arm.marking_shape_select" />

<img.area shape="rect" coords="80,204,139,446" href="../device_marking/sys/4_info_reqs.xml#Device_marking_arm.Marking" />
</img>
</imgfile.content>
