<?xml version="1.0"?>
<?xml-stylesheet 
      type="text/xsl" 
      href="../../../xsl/imgfile.xsl"
    ?> <!DOCTYPE imgfile.content SYSTEM "../../../dtd/text.ent">
<imgfile.content module="envelope" file="mimexpg1.xml">
<img src="mimexpg1.gif">
<img.area shape="polygon" coords="136,87,136,143,249,143,249,87,136,87" href="../envelope/mimexpg2.xml" />
<img.area shape="polygon" coords="280,200,280,256,476,256,476,200,280,200" href="../person_organization_assignment/mimexpg1.xml" />
<img.area shape="polygon" coords="113,0,113,56,247,56,247,0,113,0" href="../../resources/product_definition_schema/product_definition_schema.xml#product_definition_schema" />
<img.area shape="polygon" coords="1,200,1,256,143,256,143,200,1,200" href="../date_time_assignment/mimexpg1.xml" />
<img.area shape="polygon" coords="152,200,152,256,231,256,231,200,152,200" href="../approval/mimexpg1.xml" />
<img.area shape="polygon" coords="301,132,301,175,508,175,508,132,301,132" href="../product_view_definition_properties/mimexpg1.xml" />
<img.area shape="polygon" coords="315,1,315,57,503,57,503,1,315,1" href="../../resources/product_property_definition_schema/product_property_definition_schema.xml#product_property_definition_schema" />
<img.area shape="polygon" coords="0,87,0,143,113,143,113,87,0,87" href="../message/mimexpg1.xml" />
<img.area shape="polygon" coords="301,87,301,124,508,124,508,87,301,87" href="../property_assignment/mimexpg1.xml" />
</img>
</imgfile.content>
