<?xml version="1.0"?>
<?xml-stylesheet type="text/xsl" href="../../../xsl/imgfile.xsl"?>
<!DOCTYPE imgfile.content SYSTEM "../../../dtd/text.ent">
<imgfile.content module="ap242_bo_model" file="armexpg39.xml">
<img src="armexpg39.gif">
<img.area shape="rect" coords="287,214,482,235" href="../Ap242_business_object_model/sys/4_info_reqs.xml#Ap242_business_object_model_arm.information_usage_right_select" />
<img.area shape="poly" coords="432,136,439,147,609,147,616,136,609,126,439,126,432,136" href="./armexpg35.xml" />
<img.area shape="poly" coords="558,364,577,394,648,394,667,364,648,335,577,335,558,364" href="./armexpg38.xml" />
<img.area shape="poly" coords="156,54,163,65,340,65,347,54,340,44,163,44,156,54" href="./armexpg42.xml" />
<img.area shape="poly" coords="541,570,566,609,710,609,735,570,710,532,566,532,541,570" href="./armexpg38.xml" />
<img.area shape="poly" coords="432,95,439,106,542,106,549,95,542,85,439,85,432,95" href="./armexpg1.xml" />
<img.area shape="poly" coords="129,136,136,147,346,147,353,136,346,126,136,126,129,136" href="./armexpg28.xml" />
<img.area shape="poly" coords="432,177,439,188,603,188,610,177,603,167,439,167,432,177" href="./armexpg38.xml" />
<img.area shape="poly" coords="432,54,439,65,607,65,614,54,607,44,439,44,432,54" href="./armexpg31.xml" />
<img.area shape="poly" coords="140,95,147,106,334,106,341,95,334,85,147,85,140,95" href="./armexpg50.xml" />
<img.area shape="poly" coords="432,20,439,31,542,31,549,20,542,10,439,10,432,20" href="./armexpg31.xml" />
<img.area shape="poly" coords="233,177,240,188,340,188,347,177,340,167,240,167,233,177" href="./armexpg45.xml" />
<img.area shape="poly" coords="176,283,183,294,244,294,251,283,244,273,183,273,176,283" href="./armexpg36.xml" />
<img.area shape="rect" coords="277,269,492,298" href="../Ap242_business_object_model/sys/4_info_reqs.xml#Ap242_business_object_model_arm.information_usage_right_assignment" />
<img.area shape="rect" coords="343,535,426,727" href="../Ap242_business_object_model/sys/4_info_reqs.xml#Ap242_business_object_model_arm.information_right" />
<img.area shape="rect" coords="343,332,426,483" href="../Ap242_business_object_model/sys/4_info_reqs.xml#Ap242_business_object_model_arm.information_usage_right" />
<img.area shape="rect" coords="163,331,255,484" href="../Ap242_business_object_model/sys/4_info_reqs.xml#Ap242_business_object_model_arm.information_usage_right_relationship" />
</img>
</imgfile.content>
