<?xml version="1.0"?>
<?xml-stylesheet type="text/xsl" href="../../../xsl/imgfile.xsl"?>
<!DOCTYPE imgfile.content SYSTEM "../../../dtd/text.ent">
<imgfile.content module="Planned_characteristic" file="armexpg2.xml">
<img src="armexpg2.gif">
<img.area shape="rect" coords="339,447,645,474" href="../product_view_definition/sys/4_info_reqs.xml#Product_view_definition_arm.Product_view_definition" />
<img.area shape="rect" coords="37,526,343,553" href="../product_view_definition/sys/4_info_reqs.xml#Product_view_definition_arm.Product_view_definition" />
<img.area shape="rect" coords="134,160,391,187" href="../characteristic/sys/4_info_reqs.xml#Characteristic_arm.coordinated_characteristic" />
<img.area shape="rect" coords="21,10,333,37" href="../requirement_assignment/sys/4_info_reqs.xml#Requirement_assignment_arm.Requirement_assignment" />
<img.area shape="rect" coords="290,394,483,421" href="../product_rule/sys/4_info_reqs.xml#Product_rule_arm.Rule_definition" />
<img.area shape="rect" coords="565,242,714,263" href="../planned_characteristic/sys/4_info_reqs.xml#Planned_characteristic_arm.evaluation_result_value" />
<img.area shape="rect" coords="577,277,680,298" href="../planned_characteristic/sys/4_info_reqs.xml#Planned_characteristic_arm.evaluation_type" />
<img.area shape="rect" coords="338,250,436,296" href="../planned_characteristic/sys/4_info_reqs.xml#Planned_characteristic_arm.Evaluated_characteristic" />
<img.area shape="rect" coords="45,258,180,287" href="../planned_characteristic/sys/4_info_reqs.xml#Planned_characteristic_arm.Planned_characteristic" />
<img.area shape="rect" coords="10,447,171,476" href="../planned_characteristic/sys/4_info_reqs.xml#Planned_characteristic_arm.Evaluation_view_definition" />
<img.area shape="rect" coords="280,321,494,350" href="../planned_characteristic/sys/4_info_reqs.xml#Planned_characteristic_arm.Rule_based_evaluated_characteristic" />
</img>
</imgfile.content>
