<?xml version="1.0"?>
<?xml-stylesheet type="text/xsl" href="../../../xsl/imgfile.xsl"?>
<!DOCTYPE imgfile.content SYSTEM "../../../dtd/text.ent">
<imgfile.content module="Geometric_tolerance" file="armexpg3.xml">
<img src="armexpg3.gif">
<img.area shape="rect" coords="260,229,466,250" href="../geometric_tolerance/sys/4_info_reqs.xml#Geometric_tolerance_arm.geometric_tolerance_target" />
<img.area shape="rect" coords="265,393,538,414" href="../geometric_tolerance/sys/4_info_reqs.xml#Geometric_tolerance_arm.length_or_plane_angle_data_element_select" />
<img.area shape="poly" coords="542,812,549,823,683,823,690,812,683,801,549,801,542,812" href="./armexpg6.xml" />
<img.area shape="poly" coords="127,463,134,474,382,474,389,463,382,453,134,453,127,463" href="./armexpg5.xml" />
<img.area shape="poly" coords="448,366,455,377,516,377,523,366,516,356,455,356,448,366" href="./armexpg5.xml" />
<img.area shape="rect" coords="433,448,732,475" href="../value_with_unit_extension/sys/4_info_reqs.xml#Value_with_unit_extension_arm.angle_data_element" />
<img.area shape="rect" coords="447,321,751,348" href="../value_with_unit_extension/sys/4_info_reqs.xml#Value_with_unit_extension_arm.length_data_element" />
<img.area shape="rect" coords="260,163,423,190" href="../support_resource/sys/4_info_reqs.xml#Support_resource_arm.label" />
<img.area shape="rect" coords="544,197,808,224" href="../part_view_definition/sys/4_info_reqs.xml#Part_view_definition_arm.part_view_definition" />
<img.area shape="rect" coords="260,195,478,222" href="../value_with_unit/sys/4_info_reqs.xml#Value_with_unit_arm.value_with_unit" />
<img.area shape="rect" coords="536,251,684,308" href="../dimension_tolerance/sys/4_info_reqs.xml#Dimension_tolerance_arm.dimensional_location" />
<img.area shape="rect" coords="260,131,445,158" href="../support_resource/sys/4_info_reqs.xml#Support_resource_arm.identifier" />
<img.area shape="rect" coords="433,419,737,446" href="../value_with_unit_extension/sys/4_info_reqs.xml#Value_with_unit_extension_arm.length_data_element" />
<img.area shape="rect" coords="686,251,815,308" href="../dimension_tolerance/sys/4_info_reqs.xml#Dimension_tolerance_arm.dimensional_size" />
<img.area shape="rect" coords="279,988,578,1015" href="../value_with_unit_extension/sys/4_info_reqs.xml#Value_with_unit_extension_arm.angle_data_element" />
<img.area shape="rect" coords="266,356,392,377" href="../geometric_tolerance/sys/4_info_reqs.xml#Geometric_tolerance_arm.area_unit_type" />
<img.area shape="rect" coords="260,261,472,282" href="../geometric_tolerance/sys/4_info_reqs.xml#Geometric_tolerance_arm.geometric_tolerance_modifier" />
<img.area shape="rect" coords="10,97,125,446" href="../geometric_tolerance/sys/4_info_reqs.xml#Geometric_tolerance_arm.geometric_tolerance" />
<img.area shape="rect" coords="82,595,214,624" href="../geometric_tolerance/sys/4_info_reqs.xml#Geometric_tolerance_arm.cylindricity_tolerance" />
<img.area shape="rect" coords="82,805,196,834" href="../geometric_tolerance/sys/4_info_reqs.xml#Geometric_tolerance_arm.position_tolerance" />
<img.area shape="rect" coords="82,839,224,868" href="../geometric_tolerance/sys/4_info_reqs.xml#Geometric_tolerance_arm.concentricity_tolerance" />
<img.area shape="rect" coords="82,769,210,798" href="../geometric_tolerance/sys/4_info_reqs.xml#Geometric_tolerance_arm.angularity_tolerance" />
<img.area shape="rect" coords="82,874,204,903" href="../geometric_tolerance/sys/4_info_reqs.xml#Geometric_tolerance_arm.coaxiality_tolerance" />
<img.area shape="rect" coords="82,525,197,554" href="../geometric_tolerance/sys/4_info_reqs.xml#Geometric_tolerance_arm.flatness_tolerance" />
<img.area shape="rect" coords="82,699,208,728" href="../geometric_tolerance/sys/4_info_reqs.xml#Geometric_tolerance_arm.parallelism_tolerance" />
<img.area shape="rect" coords="83,946,237,975" href="../geometric_tolerance/sys/4_info_reqs.xml#Geometric_tolerance_arm.circular_runout_tolerance" />
<img.area shape="rect" coords="83,979,232,1009" href="../geometric_tolerance/sys/4_info_reqs.xml#Geometric_tolerance_arm.total_runout_tolerance" />
<img.area shape="rect" coords="10,10,125,70" href="../geometric_tolerance/sys/4_info_reqs.xml#Geometric_tolerance_arm.geometric_tolerance_relationship" />
<img.area shape="rect" coords="82,491,219,520" href="../geometric_tolerance/sys/4_info_reqs.xml#Geometric_tolerance_arm.straightness_tolerance" />
<img.area shape="rect" coords="82,665,233,694" href="../geometric_tolerance/sys/4_info_reqs.xml#Geometric_tolerance_arm.surface_profile_tolerance" />
<img.area shape="rect" coords="82,735,239,764" href="../geometric_tolerance/sys/4_info_reqs.xml#Geometric_tolerance_arm.perpendicularity_tolerance" />
<img.area shape="rect" coords="82,560,213,589" href="../geometric_tolerance/sys/4_info_reqs.xml#Geometric_tolerance_arm.roundness_tolerance" />
<img.area shape="rect" coords="82,630,216,659" href="../geometric_tolerance/sys/4_info_reqs.xml#Geometric_tolerance_arm.line_profile_tolerance" />
<img.area shape="rect" coords="82,907,205,936" href="../geometric_tolerance/sys/4_info_reqs.xml#Geometric_tolerance_arm.symmetry_tolerance" />
</img>
</imgfile.content>
