<?xml version="1.0"?>
<?xml-stylesheet 
      type="text/xsl" 
      href="../../../xsl/imgfile.xsl"
    ?> <!DOCTYPE imgfile.content SYSTEM "../../../dtd/text.ent">
<imgfile.content module="ap239_work_definition" file="mimexpg1.xml">
<img src="mimexpg1.gif">
<img.area shape="poly" coords="29,859,29,896,236,896,236,859,29,859" href="../../resources/action_schema/action_schema.xml#action_schema" />
<img.area shape="poly" coords="29,905,29,943,236,943,236,905,29,905" href="../activity_method_assignment/mimexpg1.xml" />
<img.area shape="poly" coords="312,253,312,291,519,291,519,253,312,253" href="../activity_method_characterized/mimexpg1.xml" />
<img.area shape="poly" coords="29,433,29,471,236,471,236,433,29,433" href="../activity_method_implementation/mimexpg1.xml" />
<img.area shape="poly" coords="28,669,28,707,236,707,236,669,28,669" href="../activity_method/mimexpg1.xml" />
<img.area shape="poly" coords="29,717,29,755,236,755,236,717,29,717" href="../activity/mimexpg1.xml" />
<img.area shape="poly" coords="29,244,29,281,236,281,236,244,29,244" href="../ap239_part_definition_information/mimexpg1.xml" />
<img.area shape="poly" coords="29,292,29,329,236,329,236,292,29,292" href="../ap239_task_specification_resourced/mimexpg1.xml" />
<img.area shape="poly" coords="29,623,29,660,236,660,236,623,29,623" href="../approval/mimexpg1.xml" />
<img.area shape="poly" coords="29,339,29,376,236,376,236,339,29,339" href="../attachment_slot/mimexpg1.xml" />
<img.area shape="poly" coords="29,387,29,424,236,424,236,387,29,387" href="../condition/mimexpg1.xml" />
<img.area shape="poly" coords="312,749,312,787,519,787,519,749,312,749" href="../contract/mimexpg1.xml" />
<img.area shape="poly" coords="312,704,312,741,519,741,519,704,312,704" href="../../resources/contract_schema/contract_schema.xml#contract_schema" />
<img.area shape="poly" coords="29,575,29,612,236,612,236,575,29,575" href="../date_time_assignment/mimexpg1.xml" />
<img.area shape="poly" coords="312,795,312,832,519,832,519,795,312,795" href="../document_assignment/mimexpg1.xml" />
<img.area shape="poly" coords="312,344,312,381,519,381,519,344,312,344" href="../event/mimexpg1.xml" />
<img.area shape="poly" coords="312,387,312,424,519,424,519,387,312,387" href="../file_identification/mimexpg1.xml" />
<img.area shape="poly" coords="29,811,29,848,236,848,236,811,29,811" href="../identification_assignment/mimexpg1.xml" />
<img.area shape="poly" coords="312,568,312,605,519,605,519,568,312,568" href="../interface_lifecycle/mimexpg1.xml" />
<img.area shape="poly" coords="312,523,312,560,519,560,519,523,312,523" href="../interface/mimexpg1.xml" />
<img.area shape="poly" coords="29,480,29,517,236,517,236,480,29,480" href="../management_resource_information/mimexpg1.xml" />
<img.area shape="poly" coords="29,528,29,565,236,565,236,528,29,528" href="../multi_linguism/mimexpg1.xml" />
<img.area shape="poly" coords="587,283,587,320,793,320,793,283,587,283" href="../person_organization_assignment/mimexpg1.xml" />
<img.area shape="poly" coords="29,764,29,801,236,801,236,764,29,764" href="../../resources/person_organization_schema/person_organization_schema.xml#person_organization_schema" />
<img.area shape="poly" coords="312,432,312,469,519,469,519,432,312,432" href="../product_breakdown/mimexpg1.xml" />
<img.area shape="poly" coords="29,1000,29,1037,236,1037,236,1000,29,1000" href="../../resources/product_definition_schema/product_definition_schema.xml#product_definition_schema" />
<img.area shape="poly" coords="312,931,312,968,519,968,519,931,312,931" href="../product_group/mimexpg1.xml" />
<img.area shape="poly" coords="312,659,312,696,519,696,519,659,312,659" href="../product_identification/mimexpg1.xml" />
<img.area shape="poly" coords="587,464,587,501,793,501,793,464,587,464" href="../product_view_definition/mimexpg1.xml" />
<img.area shape="poly" coords="587,509,587,547,793,547,793,509,587,509" href="../product_view_definition_relationship/mimexpg1.xml" />
<img.area shape="poly" coords="312,613,312,651,519,651,519,613,312,613" href="../project/mimexpg1.xml" />
<img.area shape="poly" coords="587,419,587,456,793,456,793,419,587,419" href="../property_assignment/mimexpg1.xml" />
<img.area shape="poly" coords="587,781,587,819,793,819,793,781,587,781" href="../required_resource_characterized/mimexpg1.xml" />
<img.area shape="poly" coords="587,373,587,411,793,411,793,373,587,373" href="../required_resource/mimexpg1.xml" />
<img.area shape="poly" coords="587,736,587,773,793,773,793,736,587,736" href="../resource_item/mimexpg1.xml" />
<img.area shape="poly" coords="312,212,312,249,519,249,519,212,312,212" href="../scheme/mimexpg1.xml" />
<img.area shape="poly" coords="587,328,587,365,793,365,793,328,587,328" href="../security_classification/mimexpg1.xml" />
<img.area shape="poly" coords="587,600,587,637,793,637,793,600,587,600" href="../task_specification/mimexpg1.xml" />
<img.area shape="poly" coords="587,691,587,728,793,728,793,691,587,691" href="../work_output_characterized/mimexpg1.xml" />
<img.area shape="poly" coords="587,645,587,683,793,683,793,645,587,645" href="../work_output/mimexpg1.xml" />
<img.area shape="poly" coords="245,8,245,55,509,55,509,8,245,8" href="../ap239_work_definition/mimexpg2.xml" />
<img.area shape="poly" coords="29,953,29,991,236,991,236,953,29,953" href="../../resources/date_time_schema/date_time_schema.xml#date_time_schema" />
<img.area shape="poly" coords="312,840,312,877,519,877,519,840,312,840" href="../certification/mimexpg1.xml" />
<img.area shape="poly" coords="312,885,312,923,519,923,519,885,312,885" href="../../resources/group_schema/group_schema.xml#group_schema" />
<img.area shape="poly" coords="312,477,312,515,519,515,519,477,312,477" href="../functional_breakdown/mimexpg1.xml" />
<img.area shape="poly" coords="587,917,587,955,793,955,793,917,587,917" href="../system_breakdown/mimexpg1.xml" />
<img.area shape="poly" coords="587,872,587,909,793,909,793,872,587,872" href="../product_version/mimexpg1.xml" />
<img.area shape="poly" coords="587,237,587,275,793,275,793,237,587,237" href="../person_organization/mimexpg1.xml" />
<img.area shape="poly" coords="312,299,312,336,519,336,519,299,312,299" href="../activity_characterized/mimexpg1.xml" />
<img.area shape="poly" coords="587,192,587,229,793,229,793,192,587,192" href="../part_view_definition/mimexpg1.xml" />
<img.area shape="poly" coords="587,147,587,184,793,184,793,147,587,147" href="../physical_breakdown/mimexpg1.xml" />
<img.area shape="poly" coords="587,827,587,864,793,864,793,827,587,827" href="../part_and_version_identification/mimexpg1.xml" />
<img.area shape="poly" coords="587,555,587,592,793,592,793,555,587,555" href="../product_as_individual/mimexpg1.xml" />
<img.area shape="poly" coords="9,197,9,235,236,235,236,197,9,197" href="../resource_management_characterized/mimexpg1.xml" />
<img.area shape="poly" coords="312,171,312,208,519,208,519,171,312,171" href="../work_order_characterized/mimexpg1.xml" />
<img.area shape="poly" coords="312,129,312,167,519,167,519,129,312,129" href="../work_request_characterized/mimexpg1.xml" />
<img.area shape="poly" coords="27,149,27,187,236,187,236,149,27,149" href="../justification/mimexpg1.xml" />
<img.area shape="poly" coords="29,104,29,141,236,141,236,104,29,104" href="../work_order/mimexpg1.xml" />
<img.area shape="poly" coords="312,88,312,125,517,125,517,88,312,88" href="../work_request/mimexpg1.xml" />
<img.area shape="poly" coords="585,55,585,92,801,92,801,55,585,55" href="../document_and_version_identification/mimexpg1.xml" />
<img.area shape="poly" coords="587,101,587,139,793,139,793,101,587,101" href="../document_definition/mimexpg1.xml" />
<img.area shape="poly" coords="19,59,19,96,207,96,207,59,19,59" href="../state_definition/mimexpg1.xml" />
<img.area shape="poly" coords="19,11,19,45,207,45,207,11,19,11" href="../state_observed/mimexpg1.xml" />
<img.area shape="poly" coords="587,293,587,331,793,331,793,293,587,293" href="../zonal_breakdown/mimexpg1.xml" />
<img.area shape="poly" coords="312,981,312,1019,516,1019,516,981,312,981" href="../../resources/state_type_schema/state_type_schema.xml#state_type_schema" />
<img.area shape="poly" coords="587,963,587,1000,793,1000,793,963,587,963" href="../../resources/state_observed_schema/state_observed_schema.xml#state_observed_schema" />
</img>
</imgfile.content>
